paketlib/__init__.py
paketlib/__main__.py
paketlib/console.py
paketlib/paket.py
paketlib/path.py
paketlib/pkcrypt.py
paketlib/protect.py
paketlib/search.py
paketlib-0.1.16.dist-info/METADATA
paketlib-0.1.16.dist-info/WHEEL
paketlib-0.1.16.dist-info/top_level.txt
paketlib-0.1.16.dist-info/RECORD
