Metadata-Version: 2.1
Name: paketlib
Version: 0.1.16
Summary: PaketSoftware lib
Author: PaketSoftware
Classifier: Programming Language :: Python :: 3
Classifier: License :: OSI Approved :: MIT License
Classifier: Operating System :: OS Independent
Requires-Python: >=3.6
Requires-Dist: requests
Requires-Dist: pystyle
Requires-Dist: bs4
